LICENSE
MANIFEST.in
README.adoc
README.md
setup.cfg
setup.py
version.txt
src/libpysdcxx/bigram_multiset.cxx
src/libpysdcxx/bigrams.cxx
src/libpysdcxx/sequence_matcher.cxx
src/libpysdcxx/unordered_bigram_multiset.cxx
src/libpysdcxx/util.hxx
src/libsdcxx/bigram_multiset.hxx
src/libsdcxx/bigrams.hxx
src/libsdcxx/sequence_matcher.hxx
src/pysdcxx/__init__.py
src/pysdcxx/bigram_multiset.py
src/pysdcxx/bigrams.py
src/pysdcxx/libpysdcxx.py
src/pysdcxx/sequence_matcher.py
src/pysdcxx/unordered_bigram_multiset.py
src/pysdcxx/util.py
src/pysdcxx.egg-info/PKG-INFO
src/pysdcxx.egg-info/SOURCES.txt
src/pysdcxx.egg-info/dependency_links.txt
src/pysdcxx.egg-info/top_level.txt